Workbook

Sheet DASHBOARD
A2: ADV LIRA | E2: PAINEL DE INDICADORES DE RECURSOS HUMANOS | Q2: Area | R2: Quantidade
Q3: Diretoria | R3: ==COUNTIF(DB_FUNCIONARIOS!AN2:AN5000, "Diretoria")
Q4: Recursos Humanos | R4: ==COUNTIF(DB_FUNCIONARIOS!AN2:AN5000, "Recursos Humanos")
A5: 🏠 Dashboard | E5: Ativos | H5: Afastados | K5: Admissoes Ano | N5: Desligados Ano | Q5: Juridico | R5: ==COUNTIF(DB_FUNCIONARIOS!AN2:AN5000, "Juridico")
E6: ==COUNTIF(DB_FUNCIONARIOS!AZ2:AZ5000, "Ativo") | H6: ==COUNTIF(DB_FUNCIONARIOS!AZ2:AZ5000, "Afastado") | K6: ==COUNTIF(DB_FUNCIONARIOS!AL2:AL5000, ">=01/01/2026") | N6: ==COUNTIF(DB_FUNCIONARIOS!AZ2:AZ5000, "Desligado") | Q6: Operacional | R6: ==COUNTIF(DB_FUNCIONARIOS!AN2:AN5000, "Operacional")
A7: 👥 Cadastro | Q7: Financeiro | R7: ==COUNTIF(DB_FUNCIONARIOS!AN2:AN5000, "Financeiro")
Q8: Tecnologia | R8: ==COUNTIF(DB_FUNCIONARIOS!AN2:AN5000, "Tecnologia")
A9: 🩹 Afastamentos
Q10: Status | R10: Qtd
A11: ⚠️ Disciplinar | Q11: Ativo | R11: ==COUNTIF(DB_FUNCIONARIOS!AZ2:AZ5000, "Ativo")
Q12: Afastado | R12: ==COUNTIF(DB_FUNCIONARIOS!AZ2:AZ5000, "Afastado")
A13: 🕒 Horas Extras | Q13: Desligado | R13: ==COUNTIF(DB_FUNCIONARIOS!AZ2:AZ5000, "Desligado")
A15: 📊 Relatorios
A22: 🚪 Sair (Logoff)

Sheet CADASTRO
A2: ADV LIRA | E2: FICHA REGISTRO DE COLABORADOR
A5: 🏠 Dashboard | E5: Buscar CPF ou Codigo: | J5: Aguardando busca ou novo cadastro...
A7: 👥 Cadastro
E8: Codigo:
A9: 🩹 Afastamentos | E9: Nome Completo:
E10: RG:
A11: ⚠️ Disciplinar | E11: CPF:
E12: Nascimento:
A13: 🕒 Horas Extras | E13: Estado Civil:
E14: Sexo:
A15: 📊 Relatorios | E15: Telefone:
E16: E-mail: | K16: Possui Deficiencia?
E17: CEP: | K17: Tipo Deficiencia:
E18: Endereco: | K18: Escolaridade:
E19: Numero / Compl: | K19: Cargo / Funcao:
E20: Bairro: | K20: Area / Depto:
E21: Cidade: | K21: Gestor Imediato:
A22: 🚪 Sair (Logoff) | E22: Estado / Pais: | K22: Data Admissao:
E23: Nome da Mae: | K23: Salario Inicial:
E24: Nome do Pai: | K24: Salario Atual:
E25: Dependentes: | K25: PIS / PASEP:
K26: CTPS / Serie / UF:
K27: Status:
E29: BENEFICIOS E INFORMACOES COMPLEMENTARES
E31: Vale Transporte: | F31: Nao | J31: Observacoes:
E32: Vale Refeicao: | F32: Nao
E33: Vale Alimentacao: | F33: Nao
E34: Plano de Saude: | F34: Nao
E35: Plano Odonto: | F35: Nao
E36: Seguro de Vida: | F36: Nao

Sheet AFASTAMENTOS
A2: ADV LIRA | E2: HISTORICO DE AFASTAMENTOS & LICENCAS
A5: 🏠 Dashboard | E5: Codigo | F5: Nome Colaborador | G5: Data Inicio | H5: Data Fim | I5: Tipo Afastamento | J5: Descricao | K5: Status
A7: 👥 Cadastro
A9: 🩹 Afastamentos
A11: ⚠️ Disciplinar
A13: 🕒 Horas Extras
A15: 📊 Relatorios
A22: 🚪 Sair (Logoff)

Sheet DISCIPLINAR
A2: ADV LIRA | E2: CONTROLE DE PENALIDADES DISCIPLINARES
A5: 🏠 Dashboard | E5: Codigo | F5: Nome Colaborador | G5: Data Ocorrencia | H5: Tipo Penalidade | I5: Descricao / Motivo | J5: Gestor Solicitante
A7: 👥 Cadastro
A9: 🩹 Afastamentos
A11: ⚠️ Disciplinar
A13: 🕒 Horas Extras
A15: 📊 Relatorios
A22: 🚪 Sair (Logoff)

Sheet HORAS_EXTRAS
A2: ADV LIRA | E2: CONTROLE DE HORAS EXTRAS & BANCO DE HORAS
A5: 🏠 Dashboard | E5: Codigo | F5: Nome Colaborador | G5: Data Ocorrencia | H5: Horas Extras (h) | I5: Horas Atraso (h) | J5: Justificativa
A7: 👥 Cadastro
A9: 🩹 Afastamentos
A11: ⚠️ Disciplinar
A13: 🕒 Horas Extras
A15: 📊 Relatorios
A22: 🚪 Sair (Logoff)

Sheet RELATORIOS
A2: ADV LIRA | E2: PAINEL DE EXPORTACAO E RELATORIOS GERENCIAIS
H4: F0001
A5: 🏠 Dashboard | E5: FICHA INDIVIDUAL DO COLABORADOR (PREVIEW)
A7: 👥 Cadastro | E7: Buscar Codigo: | H7: ==XLOOKUP(H4, DB_FUNCIONARIOS!E:E, DB_FUNCIONARIOS!F:F, "Vazio")
A9: 🩹 Afastamentos | E9: Nome: | F9: ==XLOOKUP(H4, DB_FUNCIONARIOS!E:E, DB_FUNCIONARIOS!F:F, "Nao Localizado") | J9: Cargo: | K9: ==XLOOKUP(H4, DB_FUNCIONARIOS!E:E, DB_FUNCIONARIOS!AM:AM, "-")
E10: CPF: | F10: ==XLOOKUP(H4, DB_FUNCIONARIOS!E:E, DB_FUNCIONARIOS!H:H, "-") | J10: Admissao: | K10: ==XLOOKUP(H4, DB_FUNCIONARIOS!E:E, DB_FUNCIONARIOS!AL:AL, "-")
A11: ⚠️ Disciplinar | E11: Telefone: | F11: ==XLOOKUP(H4, DB_FUNCIONARIOS!E:E, DB_FUNCIONARIOS!L:L, "-") | J11: Email: | K11: ==XLOOKUP(H4, DB_FUNCIONARIOS!E:E, DB_FUNCIONARIOS!K:K, "-")
E12: Salario Atual: | F12: ==XLOOKUP(H4, DB_FUNCIONARIOS!E:E, DB_FUNCIONARIOS!AS:AS, 0) | J12: Status: | K12: ==XLOOKUP(H4, DB_FUNCIONARIOS!E:E, DB_FUNCIONARIOS!AZ:AZ, "-")
A13: 🕒 Horas Extras
A15: 📊 Relatorios
A22: 🚪 Sair (Logoff)

Sheet DB_FUNCIONARIOS
E1: Codigo | F1: Nome Completo | G1: RG | H1: CPF | I1: Data Nascimento | J1: Estado Civil | K1: E-mail | L1: Telefone | M1: Endereco | N1: Numero | O1: Complemento | P1: Bairro | Q1: Cidade | R1: Estado | S1: CEP | T1: Nome da Mae | U1: Nome do Pai | V1: Dependentes | W1: Possui Deficiencia | X1: Tipo Deficiencia | Y1: Caminho Foto | Z1: Observacoes | AA1: Pais | AB1: Sexo | AC1: Altura | AD1: Escolaridade | AE1: Profissao | AF1: Empresa | AG1: PIS | AH1: CTPS | AI1: Serie | AJ1: UF Documento | AK1: Data Emissao | AL1: Data Admissao | AM1: Cargo | AN1: Area | AO1: Departamento | AP1: Gestor | AQ1: Atividades | AR1: Salario Inicial | AS1: Salario Atual | AT1: Vale Transporte | AU1: Vale Refeicao | AV1: Vale Alimentacao | AW1: Plano de Saude | AX1: Plano Odontologico | AY1: Seguro de Vida | AZ1: Status
E2: F0001 | F2: Lucas de Melo Silva | G2: 11.222.333-4 | H2: 111.222.333-44 | I2: 15/04/1990 | J2: Casado(a) | K2: lucas.melo@empresa.com | L2: (11) 98888-7777 | M2: Av Paulista | N2: 1000 | O2: Apto 12 | P2: Bela Vista | Q2: Sao Paulo | R2: SP | S2: 01311-100 | T2: Maria de Melo | U2: Jose Silva | V2: 1 | W2: Nao | Z2: Nenhuma | AA2: Brasil | AB2: Masculino | AC2: 1.75 | AD2: Superior Completo | AE2: Advogado | AF2: ADV Lira Melo | AG2: 123.45678.90-1 | AH2: 98765 | AI2: 001-A | AJ2: SP | AK2: 10/10/2015 | AL2: 01/03/2026 | AM2: Advogado Pleno | AN2: Juridico | AO2: Contencioso | AP2: Dr. Lira Melo | AQ2: Audiencias e peticoes | AR2: 5000 | AS2: 5200 | AT2: Sim | AU2: Sim | AV2: Nao | AW2: Sim | AX2: Sim | AY2: Nao | AZ2: Ativo
E3: F0002 | F3: Camila Lira Santos | G3: 22.333.444-5 | H3: 222.333.444-55 | I3: 22/08/1993 | J3: Solteiro(a) | K3: camila.lira@empresa.com | L3: (11) 97777-6666 | M3: Rua Augusta | N3: 500 | P3: Consolacao | Q3: Sao Paulo | R3: SP | S3: 01305-000 | T3: Ana Lira | U3: Carlos Santos | V3: 0 | W3: Nao | Z3: Ficha limpa | AA3: Brasil | AB3: Feminino | AC3: 1.65 | AD3: Pós-Graduação | AE3: Controller | AF3: ADV Lira Melo | AG3: 234.56789.01-2 | AH3: 87654 | AI3: 002-B | AJ3: SP | AK3: 12/11/2016 | AL3: 15/04/2026 | AM3: Controller Juridico | AN3: Financeiro | AO3: Administrativo | AP3: Dr. Lira Melo | AQ3: Fluxo de caixa e relatorios | AR3: 6000 | AS3: 6000 | AT3: Nao | AU3: Sim | AV3: Sim | AW3: Sim | AX3: Nao | AY3: Sim | AZ3: Ativo
E4: F0003 | F4: Felipe Santos Oliveira | G4: 33.444.555-6 | H4: 333.444.555-66 | I4: 10/12/1988 | J4: Casado(a) | K4: felipe.santos@empresa.com | L4: (11) 96666-5555 | M4: Av Consolacao | N4: 2000 | O4: Sala 3 | P4: Cerqueira Cesar | Q4: Sao Paulo | R4: SP | S4: 01416-000 | T4: Julia Santos | U4: Marcos Oliveira | V4: 2 | W4: Nao | Z4: Destaque do ano | AA4: Brasil | AB4: Masculino | AC4: 1.80 | AD4: Superior Completo | AE4: TI Specialist | AF4: ADV Lira Melo | AG4: 345.67890.12-3 | AH4: 76543 | AI4: 003-C | AJ4: SP | AK4: 05/05/2018 | AL4: 01/05/2026 | AM4: Analista de TI | AN4: Tecnologia | AO4: TI | AP4: Dr. Lira Melo | AQ4: Suporte a servidores e rede | AR4: 4500 | AS4: 4800 | AT4: Sim | AU4: Sim | AV4: Nao | AW4: Sim | AX4: Sim | AY4: Nao | AZ4: Ativo
E5: F0004 | F5: Juliana Ribeiro Costa | G5: 44.555.666-7 | H5: 444.555.666-77 | I5: 05/02/1995 | J5: Solteiro(a) | K5: juliana.costa@empresa.com | L5: (11) 95555-4444 | M5: Alameda Santos | N5: 800 | O5: Apto 84 | P5: Jardins | Q5: Sao Paulo | R5: SP | S5: 01419-001 | T5: Lucia Ribeiro | U5: Paulo Costa | V5: 0 | W5: Nao | Z5: Nenhuma | AA5: Brasil | AB5: Feminino | AC5: 1.68 | AD5: Superior Incompleto | AE5: Estagiaria | AF5: ADV Lira Melo | AG5: 456.78901.23-4 | AH5: 65432 | AI5: 004-D | AJ5: SP | AK5: 20/01/2020 | AL5: 01/06/2026 | AM5: Estagiario | AN5: Diretoria | AO5: Juridico | AP5: Dr. Lira Melo | AQ5: Apoio a peticoes e arquivo | AR5: 1500 | AS5: 1500 | AT5: Sim | AU5: Nao | AV5: Sim | AW5: Sim | AX5: Nao | AY5: Nao | AZ5: Ativo
E6: F0005 | F6: Bruno Souza Lima | G6: 55.666.777-8 | H6: 555.666.777-88 | I6: 30/09/1985 | J6: Divorciado(a) | K6: bruno.lima@empresa.com | L6: (11) 94444-3333 | M6: Rua Pamplona | N6: 1200 | P6: Jardim Paulista | Q6: Sao Paulo | R6: SP | S6: 01405-001 | T6: Beatriz Souza | U6: Andre Lima | V6: 1 | W6: Nao | Z6: Diligente | AA6: Brasil | AB6: Masculino | AC6: 1.78 | AD6: Superior Completo | AE6: Gerente RH | AF6: ADV Lira Melo | AG6: 567.89012.34-5 | AH6: 54321 | AI6: 005-E | AJ6: SP | AK6: 15/09/2010 | AL6: 10/01/2026 | AM6: Gerente de RH | AN6: Recursos Humanos | AO6: RH | AP6: Dr. Lira Melo | AQ6: Recrutamento e folha | AR6: 8000 | AS6: 8500 | AT6: Nao | AU6: Sim | AV6: Sim | AW6: Sim | AX6: Sim | AY6: Sim | AZ6: Ativo
E7: F0006 | F7: Amanda Oliveira Mello | G7: 66.777.888-9 | H7: 666.777.888-99 | I7: 12/03/1991 | J7: Solteiro(a) | K7: amanda.mello@empresa.com | L7: (21) 99999-8888 | M7: Av Atlantica | N7: 400 | O7: Cob 01 | P7: Copacabana | Q7: Rio de Janeiro | R7: RJ | S7: 22020-002 | T7: Carla Oliveira | U7: Ricardo Mello | V7: 0 | W7: Nao | Z7: Home office | AA7: Brasil | AB7: Feminino | AC7: 1.70 | AD7: Superior Completo | AE7: Advogada Trabalhista | AF7: ADV Lira Melo | AG7: 678.90123.45-6 | AH7: 43210 | AI7: 006-F | AJ7: RJ | AK7: 02/02/2017 | AL7: 01/02/2026 | AM7: Advogado Pleno | AN7: Juridico | AO7: Trabalhista | AP7: Dr. Lira Melo | AQ7: Processos trabalhistas | AR7: 5200 | AS7: 5200 | AT7: Nao | AU7: Sim | AV7: Nao | AW7: Sim | AX7: Nao | AY7: Nao | AZ7: Ativo
E8: F0007 | F8: Rafael Costa Rocha | G8: 77.888.999-0 | H8: 777.888.999-00 | I8: 12/06/1994 | J8: Casado(a) | K8: rafael.rocha@empresa.com | L8: (11) 93333-2222 | M8: Rua Bela Cintra | N8: 1500 | O8: Apto 91 | P8: Consolacao | Q8: Sao Paulo | R8: SP | S8: 01415-001 | T8: Sandra Costa | U8: Arthur Rocha | V8: 1 | W8: Nao | Z8: Destaque Junho | AA8: Brasil | AB8: Masculino | AC8: 1.76 | AD8: Superior Completo | AE8: Analista Financeiro | AF8: ADV Lira Melo | AG8: 789.01234.56-7 | AH8: 32109 | AI8: 007-G | AJ8: SP | AK8: 18/06/2019 | AL8: 01/01/2026 | AM8: Analista Financeiro Jr | AN8: Financeiro | AO8: Contas a Pagar | AP8: Camila Lira Santos | AQ8: Controle de notas e faturas | AR8: 3500 | AS8: 3700 | AT8: Sim | AU8: Sim | AV8: Nao | AW8: Sim | AX8: Sim | AY8: Nao | AZ8: Ativo
E9: F0008 | F9: Mariana Rocha Rezende | G9: 88.999.000-1 | H9: 888.999.000-11 | I9: 25/07/1992 | J9: Solteiro(a) | K9: mariana.rezende@empresa.com | L9: (31) 98888-5555 | M9: Av Afonso Pena | N9: 3000 | P9: Centro | Q9: Belo Horizonte | R9: MG | S9: 30130-009 | T9: Marta Rocha | U9: Eduardo Rezende | V9: 0 | W9: Nao | Z9: Filial BH | AA9: Brasil | AB9: Feminino | AC9: 1.62 | AD9: Ensino Medio | AE9: Secretaria | AF9: ADV Lira Melo | AG9: 890.12345.67-8 | AH9: 21098 | AI9: 008-H | AJ9: MG | AK9: 09/09/2015 | AL9: 01/04/2026 | AM9: Secretaria Executiva | AN9: Operacional | AO9: Secretaria | AP9: Dr. Lira Melo | AQ9: Atendimento e agenda | AR9: 2500 | AS9: 2500 | AT9: Sim | AU9: Sim | AV9: Nao | AW9: Sim | AX9: Nao | AY9: Nao | AZ9: Ativo
E10: F0009 | F10: Gustavo Lima Nogueira | G10: 99.000.111-2 | H10: 999.000.111-22 | I10: 18/11/1987 | J10: Casado(a) | K10: gustavo.nogueira@empresa.com | L10: (11) 92222-1111 | M10: Rua Haddock Lobo | N10: 600 | O10: Apto 32 | P10: Cerqueira Cesar | Q10: Sao Paulo | R10: SP | S10: 01414-001 | T10: Regina Lima | U10: Newton Nogueira | V10: 3 | W10: Nao | Z10: Pai de 3 | AA10: Brasil | AB10: Masculino | AC10: 1.82 | AD10: Pós-Graduação | AE10: Advogado Tributario | AF10: ADV Lira Melo | AG10: 901.23456.78-9 | AH10: 10987 | AI10: 009-I | AJ10: SP | AK10: 30/11/2012 | AL10: 01/01/2026 | AM10: Advogado Senior | AN10: Juridico | AO10: Tributario | AP10: Dr. Lira Melo | AQ10: Pareceres e defesas fiscais | AR10: 8500 | AS10: 9000 | AT10: Nao | AU10: Sim | AV10: Sim | AW10: Sim | AX10: Sim | AY10: Sim | AZ10: Ativo
E11: F0010 | F11: Beatriz Almeida Silveira | G11: 12.345.678-9 | H11: 123.456.789-01 | I11: 03/11/1996 | J11: Solteiro(a) | K11: beatriz.silveira@empresa.com | L11: (11) 91111-0000 | M11: Rua da Consolacao | N11: 2500 | P11: Consolacao | Q11: Sao Paulo | R11: SP | S11: 01301-100 | T11: Sonia Almeida | U11: Renato Silveira | V11: 0 | W11: Nao | Z11: Nenhuma | AA11: Brasil | AB11: Feminino | AC11: 1.67 | AD11: Ensino Tecnico | AE11: Auxiliar RH | AF11: ADV Lira Melo | AG11: 012.34567.89-0 | AH11: 09876 | AI11: 010-J | AJ11: SP | AK11: 12/12/2021 | AL11: 15/05/2026 | AM11: Auxiliar de RH | AN11: Recursos Humanos | AO11: RH | AP11: Bruno Souza Lima | AQ11: Controle de ponto e arquivos | AR11: 2000 | AS11: 2000 | AT11: Sim | AU11: Sim | AV11: Nao | AW11: Sim | AX11: Nao | AY11: Nao | AZ11: Ativo

Sheet DB_AFASTAMENTOS
E1: Codigo | F1: Nome | G1: Data Inicio | H1: Data Fim | I1: Tipo | J1: Descricao | K1: Status

Sheet DB_DISCIPLINAR
E1: Codigo | F1: Nome | G1: Data | H1: Tipo | I1: Descricao | J1: Gestor

Sheet DB_HORAS_EXTRAS
E1: Codigo | F1: Nome | G1: Data | H1: Horas Extras | I1: Horas Atraso | J1: Justificativa
